phyal/__init__.py
phyal-0.4.1.dist-info/METADATA
phyal-0.4.1.dist-info/WHEEL
phyal-0.4.1.dist-info/RECORD
