Metadata-Version: 2.1
Name: phyal
Version: 0.4.1
Summary: Quickly build websites without the hassle of HTML
License: MIT
Author: SalladShooter
Author-email: 139503084+SalladShooter@users.noreply.github.com
Requires-Python: >=3.10,<4.0
Classifier: License :: OSI Approved :: MIT License
Classifier: Programming Language :: Python :: 3
Classifier: Programming Language :: Python :: 3.10
Classifier: Programming Language :: Python :: 3.11
